aiida_icl/__init__.py
aiida_icl/schedulers/__init__.py
aiida_icl/schedulers/pbspro_cx1.py
aiida_icl/tests/__init__.py
aiida_icl/tests/test_pbspro_cx1.py
aiida_icl/tests/test_utils.py
aiida_icl/utils/__init__.py
aiida_icl/utils/computer_cx1.py
aiida_icl/utils/crystal_code.py
aiida_icl/utils/cx1_resources.py
aiida_icl-0.3.4.dist-info/LICENSE
aiida_icl-0.3.4.dist-info/METADATA
aiida_icl-0.3.4.dist-info/WHEEL
aiida_icl-0.3.4.dist-info/entry_points.txt
aiida_icl-0.3.4.dist-info/top_level.txt
aiida_icl-0.3.4.dist-info/RECORD
